functions_by_alextsiasto/README.md
functions_by_alextsiasto/math_functions.py
functions_by_alextsiasto-0.3.0.dist-info/WHEEL
functions_by_alextsiasto-0.3.0.dist-info/METADATA
functions_by_alextsiasto-0.3.0.dist-info/RECORD
