Metadata-Version: 2.1
Name: functions-by-alextsiasto
Version: 0.3.0
Summary: This is our test project
Author: Alex Tsiasto
Author-email: alex.tsiasto@gmail.com
Requires-Python: >=3.10,<4.0
Classifier: Programming Language :: Python :: 3
Classifier: Programming Language :: Python :: 3.10
Classifier: Programming Language :: Python :: 3.11
